Metadata-Version: 1.0
Name: funny123
Version: 0.2
Summary: The funniest joke in the world
Home-page: UNKNOWN
Author: Flying Circus
Author-email: flyingcircus@example.com
License: MIT
Platform: UNKNOWN
